datacore/__init__.py
datacore/datacore_restlike.py
datacore/exceptions.py
datacore/types.py
datacore_python_client-1.4.1.dist-info/LICENSE
datacore_python_client-1.4.1.dist-info/METADATA
datacore_python_client-1.4.1.dist-info/WHEEL
datacore_python_client-1.4.1.dist-info/top_level.txt
datacore_python_client-1.4.1.dist-info/RECORD
