Metadata-Version: 2.1
Name: datacore-python-client
Version: 1.4.1
Summary: Extensible Python Client for accessing datacore RESTfully
Home-page: https://github.com/Bodaclick/datacore-python-client
Author: Vincent Medina
Author-email: vincent@everymundo.com
License: UNKNOWN
Keywords: em datacore everymundo
Platform: UNKNOWN
Classifier: Development Status :: 4 - Beta
Classifier: Programming Language :: Python :: 3.5
Requires-Dist: requests
